gpteval3d/__init__.py
gpteval3d/gpt_eval_alpha.py
gpteval3d/utils/__init__.py
gpteval3d/utils/glide_elo.py
gpteval3d/utils/gpt4v_utils.py
gpteval3d/utils/image_utils.py
gpteval3d/utils/t23d_tournament.py
gpteval3d-0.0.1.dist-info/LICENSE
gpteval3d-0.0.1.dist-info/METADATA
gpteval3d-0.0.1.dist-info/WHEEL
gpteval3d-0.0.1.dist-info/top_level.txt
gpteval3d-0.0.1.dist-info/RECORD
