Metadata-Version: 2.1
Name: gpteval3d
Version: 0.0.1
Summary: A pip package for GPTEval3D
Project-URL: Homepage, https://gpteval3d.github.io/
Project-URL: Issues, https://github.com/3DTopia/GPTEval3D/issues
Classifier: Programming Language :: Python :: 3
Classifier: License :: OSI Approved :: MIT License
Classifier: Operating System :: OS Independent
Requires-Python: >=3.8
License-File: LICENSE
Requires-Dist: openai
Requires-Dist: tqdm >=4.28.1
Requires-Dist: numpy >=1.14.3
Requires-Dist: Pillow
Requires-Dist: torch >=1.10.0
